qa_genie/__init__.py
qa_genie/qa_genie_fns.py
qa_genie-1.0.0a4.dist-info/METADATA
qa_genie-1.0.0a4.dist-info/WHEEL
qa_genie-1.0.0a4.dist-info/top_level.txt
qa_genie-1.0.0a4.dist-info/RECORD
