Metadata-Version: 2.1
Name: qa_genie
Version: 1.0.0a4
Summary: Generating Question Answer Database from Unstructured Text
Author: Irsh Vijayvargia
Author-email: <irsh.iitkgp@gmail.com>
License: The Unlicense
Project-URL: GitHub, https://github.com/1rsh/qa-genie
Keywords: python,question generation,question answer,nlp,llm,llm for question answering,huggingface
Classifier: Development Status :: 3 - Alpha
Classifier: Intended Audience :: Developers
Classifier: Programming Language :: Python :: 3
Classifier: Topic :: Utilities
Classifier: Operating System :: Unix
Classifier: Operating System :: MacOS :: MacOS X
Classifier: Operating System :: Microsoft :: Windows
Requires-Python: >=3.9
Requires-Dist: hugchat ==0.3.0
Requires-Dist: pandas
Requires-Dist: tqdm
